PatrowlArsenalSDK/__init__.py
PatrowlArsenalSDK/api.py
PatrowlArsenalSDK/constants.py
PatrowlArsenalSDK/exceptions.py
PatrowlArsenalSDK-1.0.1.dist-info/LICENSE
PatrowlArsenalSDK-1.0.1.dist-info/METADATA
PatrowlArsenalSDK-1.0.1.dist-info/WHEEL
PatrowlArsenalSDK-1.0.1.dist-info/top_level.txt
PatrowlArsenalSDK-1.0.1.dist-info/RECORD
