Metadata-Version: 2.1
Name: PatrowlArsenalSDK
Version: 1.0.1
Summary: Python API for PatrowlArsenal (Pro editions)
Home-page: https://github.com/Patrowl/PatrowlArsenal
Author: Nicolas Mattiocco
Author-email: getsupport@patrowl.io
License: AGPLv3
Platform: UNKNOWN
